.gitignore
LICENSE
README.md
setup.py
.idea/.gitignore
.idea/git-repeat.iml
.idea/misc.xml
.idea/modules.xml
.idea/vcs.xml
.idea/codeStyles/codeStyleConfig.xml
.idea/inspectionProfiles/profiles_settings.xml
src/git_repeat/__init__.py
src/git_repeat/main.py
src/git_repeat.egg-info/PKG-INFO
src/git_repeat.egg-info/SOURCES.txt
src/git_repeat.egg-info/dependency_links.txt
src/git_repeat.egg-info/entry_points.txt
src/git_repeat.egg-info/not-zip-safe
src/git_repeat.egg-info/requires.txt
src/git_repeat.egg-info/top_level.txt
src/git_repeat/helper/__init__.py
src/git_repeat/helper/actions.py
src/git_repeat/helper/differences.py