Metadata-Version: 2.1
Name: git-repeat
Version: 0.1.4
Summary: Remove repetitive tasks from your development workflow by using git diffs to replicate work already done
Home-page: https://github.com/p0intR/git-repeat
Author: p0intR
License: GPLv3
Project-URL: Source, https://github.com/p0intR/git-repeat
Keywords: git-repeat,python
Platform: UNKNOWN
Classifier: Programming Language :: Python :: 3
Classifier: License :: OSI Approved :: GNU General Public License v3 (GPLv3)
Classifier: Operating System :: OS Independent
Requires-Python: >=3.7
License-File: LICENSE
